awhere/__init__.py
awhere/py.typed
awhere/tests/__init__.py
awhere/tests/test_mod.py
awhere-0.0.1.dist-info/LICENSE
awhere-0.0.1.dist-info/METADATA
awhere-0.0.1.dist-info/WHEEL
awhere-0.0.1.dist-info/RECORD
