Metadata-Version: 2.1
Name: awhere
Version: 0.0.1
Summary: Agents Anywhere - An agentic workflow framework
Author: Al Wonder
Author-email: al@yiwonder.com
Requires-Python: >=3.10,<4.0
Classifier: Programming Language :: Python :: 3
Classifier: Programming Language :: Python :: 3.10
Classifier: Programming Language :: Python :: 3.11
Classifier: Programming Language :: Python :: 3.12
Provides-Extra: all
Requires-Dist: dynaconf (>=3.2.6,<4.0.0)
Requires-Dist: fastapi (>=0.115.4,<0.116.0)
Requires-Dist: pydantic (>=2.9.2,<3.0.0)
Requires-Dist: uvicorn (>=0.32.0,<0.33.0)
